uugai_python_kerberos_vault/KerberosVault.py
uugai_python_kerberos_vault/__init__.py
uugai_python_kerberos_vault-1.2.0.dist-info/METADATA
uugai_python_kerberos_vault-1.2.0.dist-info/WHEEL
uugai_python_kerberos_vault-1.2.0.dist-info/top_level.txt
uugai_python_kerberos_vault-1.2.0.dist-info/RECORD
