Metadata-Version: 2.1
Name: uugai-python-kerberos-vault
Version: 1.2.0
Summary: Kerberos Vault Python library for interacting with the Kerberos Vault.
Home-page: UNKNOWN
Author: uug.ai
Author-email: support@uug.ai
License: UNKNOWN
Platform: UNKNOWN
Requires-Dist: boto3 (==1.34.110)
Requires-Dist: botocore (==1.34.110)
Requires-Dist: certifi (==2024.2.2)
Requires-Dist: charset-normalizer (==3.3.2)
Requires-Dist: confluent-kafka (==2.4.0)
Requires-Dist: idna (==3.7)
Requires-Dist: jmespath (==1.0.1)
Requires-Dist: pika (==1.3.2)
Requires-Dist: python-dateutil (==2.9.0.post0)
Requires-Dist: python-queue-reader (==1.2)
Requires-Dist: requests (==2.32.2)
Requires-Dist: s3transfer (==0.10.1)
Requires-Dist: setuptools (==70.0.0)
Requires-Dist: six (==1.16.0)
Requires-Dist: urllib3 (==2.2.1)
